Workbook

Sheet Roadmap
A1: Portable Aimbot Target - 26-Week Roadmap
A2: Week 1 = w/c 2026-08-03. Phase 1 ships a usable workshop target by Week 6. Update Status; the Dashboard rolls up.
A4: Wk | B4: Week of | C4: Phase | D4: Work item | E4: Deliverable / exit criterion | F4: Depends on | G4: Days | H4: Status | I4: Risk
A5: 1 | B5: 46237 | C5: 1 Workshop target | D5: Freeze head-to-base interface spec (REQ-M6) | E5: Bolt/slot pattern, vertical datum, single 24V+data connector. Written down and treated as frozen. | F5: - | G5: 2 | H5: Not started | I5: -
A6: 1 | B6: 46237 | C6: 1 Workshop target | D6: Define transport envelope + weight budget baseline | E6: Case shape candidates costed; every head part gets a max-dimension and mass allocation before it is designed. | F6: - | G6: 1.5 | H6: Not started | I6: R3
A7: 1 | B7: 46237 | C7: 1 Workshop target | D7: Confirm fabrication access (Q7) | E7: 3D printer / machining / hand-cut only. Sets realistic effort for every mechanical part. | F7: - | G7: 0.5 | H7: Not started | I7: -
A8: 2 | B8: 46244 | C8: 1 Workshop target | D8: Head hub + arm design, inertia budgeted (REQ-M1, M2) | E8: Head inertia estimated BEFORE build; plate radius minimised (inertia scales with r^2). | F8: Interface | G8: 4 | H8: Not started | I8: R9
A9: 2 | B9: 46244 | C9: 1 Workshop target | D9: Workshop base - deliberately crude, heavy, ballasted (REQ-M7) | E9: Steel plate and ballast. No design effort spent here on purpose. | F9: Interface | G9: 1 | H9: Not started | I9: -
A10: 3 | B10: 46251 | C10: 1 Workshop target | D10: Fabricate head; route wiring through GM6020 hollow shaft (REQ-M4) | E10: Head assembled. 18mm hollow shaft carries power/data on the rotation axis. | F10: Design | G10: 4 | H10: Not started | I10: -
A11: 3 | B11: 46251 | C11: 1 Workshop target | D11: Joint design pass: locate vs. clamp on every joint (REQ-M10..M13) | E11: Every structural joint has a locating feature AND a separate preload element. All fasteners captive. | F11: Head | G11: 2 | H11: Not started | I11: R1
A12: 4 | B12: 46258 | C12: 1 Workshop target | D12: Motor control: 0.25-3.0 rev/s, speed hold within 2% (REQ-M2) | E12: Commanded vs. actual logged. Static hold mode works. Spin-up time measured. | F12: Head | G12: 3 | H12: Not started | I12: R9
A13: 4 | B13: 46258 | C13: 1 Workshop target | D13: Safety: hardware E-stop, balance verification, guarding (R11) | E13: E-stop cuts motor power in HARDWARE. Balance checked before first full-speed run. | F13: Motor ctrl | G13: 1.5 | H13: Not started | I13: R10
A14: 5 | B14: 46265 | C14: 1 Workshop target | D14: Endurance session + full joint re-check (R1) | E14: Run at full speed for a realistic session, then inspect every joint. Loose joints found NOW, not in month 5. | F14: Safety | G14: 1.5 | H14: Not started | I14: R1
A15: 5 | B15: 46265 | C15: 1 Workshop target | D15: Weigh every head part against the budget | E15: Actual masses replace estimates in the Weight Budget tab. | F15: Head | G15: 0.5 | H15: Not started | I15: R3
A16: 6 | B16: 46272 | C16: 1 Workshop target | D16: Phase 1 acceptance: a TEAMMATE runs a full session unaided (M2) | E16: Someone who did not build it sets up and practises without asking how. Tests the design, not your memory. | F16: Endurance | G16: 1 | H16: Not started | I16: R5
... A42: 26 | B42: 46412 | C42: 4 Travel kit | D42: Travel documentation: packout card, customs list, setup card | E42: One page. Lives in the case. | F42: Fixes | G42: 1.5 | H42: Not started | I42: -
F44: TOTAL EFFORT (solo-days) | G44: =SUM(G5:G42) -> 82
F45: Available (26 wks x 2.5 days/wk, in-season) | G45: 65
F46: Headroom (negative = overcommitted) | G46: =G45-G44 -> -17
A48: Phase 1 alone is ~22 days and delivers the training tool that removes the robot dependency. Every later phase is independently useful.
A49: If headroom is negative, the intended sacrifice order is: Phase 4 polish, then Phase 3 UI depth, then the rail. Phase 1 is never sacrificed.

Sheet Dashboard
A1: Dashboard
A2: Formulas over the other tabs - updates as you edit Status.
A4: PROGRESS
A5: Total work items | B5: =COUNTA(Roadmap!D5:D42)-COUNTIF(Roadmap!C5:C42,"GATE") -> 35
A6: Done | B6: =COUNTIF(Roadmap!H5:H42,"Done") -> 0
A7: In progress | B7: =COUNTIF(Roadmap!H5:H42,"In progress") -> 0
A8: Blocked | B8: =COUNTIF(Roadmap!H5:H42,"Blocked") -> 0
A9: % complete | B9: =IFERROR(B6/B5,0) -> 0
A12: EFFORT BY PHASE (solo-days)
A13: Phase | B13: Planned | C13: Done | D13: % done
A14: 1 Workshop target | B14: =SUMIF(Roadmap!$C$5:$C$42,$A14,Roadmap!$G$5:$G$42) -> 22.5 | C14: =SUMIFS(Roadmap!$G$5:$G$42,Roadmap!$C$5:$C$42,$A14,Roadmap!$H$5:$H$42,"Done") -> 0 | D14: =IFERROR(C14/B14,0) -> 0
A15: 2 Rail | B15: =SUMIF(Roadmap!$C$5:$C$42,$A15,Roadmap!$G$5:$G$42) -> 10 | C15: =SUMIFS(Roadmap!$G$5:$G$42,Roadmap!$C$5:$C$42,$A15,Roadmap!$H$5:$H$42,"Done") -> 0 | D15: =IFERROR(C15/B15,0) -> 0
A16: 3 Plates + UI | B16: =SUMIF(Roadmap!$C$5:$C$42,$A16,Roadmap!$G$5:$G$42) -> 28 | C16: =SUMIFS(Roadmap!$G$5:$G$42,Roadmap!$C$5:$C$42,$A16,Roadmap!$H$5:$H$42,"Done") -> 0 | D16: =IFERROR(C16/B16,0) -> 0
A17: 4 Travel kit | B17: =SUMIF(Roadmap!$C$5:$C$42,$A17,Roadmap!$G$5:$G$42) -> 21.5 | C17: =SUMIFS(Roadmap!$G$5:$G$42,Roadmap!$C$5:$C$42,$A17,Roadmap!$H$5:$H$42,"Done") -> 0 | D17: =IFERROR(C17/B17,0) -> 0
A18: TOTAL | B18: =SUM(B14:B17) -> 82 | C18: =SUM(C14:C17) -> 0 | D18: =IFERROR(C18/B18,0) -> 0
A21: TRANSPORT CHECK (live from the Weight Budget and Packing tabs)
A22: Projected packed weight (kg) | B22: ='Weight Budget'!C19 -> 18.5875
A23: Airline limit (kg) | B23: =23 -> 23
A24: Weight margin (kg) | B24: =B23-B22 -> 4.4125
A25: Weight verdict | B25: =IF(B22<=23,IF(B22<=20,"PASS with margin","PASS - tight"),"FAIL - over limit") -> PASS with margin
A26: Case linear sum (cm) | B26: =Packing!C7+Packing!C8+Packing!C9 -> 158
A27: Airline limit (cm) | B27: =158 -> 158
A28: Size verdict | B28: =IF(B26<=158,"PASS","FAIL - over limit") -> PASS
A31: GATES
A32: Gate | B32: Week | C32: Test | D32: Action on failure
A33: Adoption | B33: 6 | C33: Does a team member reach for it unprompted, and run it unaided? | D33: Understand why not before adding rail, sensors or a suitcase to it
A34: Plate gate | B34: 10 | C34: Prototype plate RMS <= 25 mm on held-out grid positions | D34: Do not build four. Ship with stock plates + referee counting
A35: Packing test | B35: 20-21 | C35: Full dry-run packout under 23 kg and 158 cm linear | D35: Decide deliberately: oversize fee, freight, or workshop-only
A36: Dry run | B36: 24 | C36: Teammate assembles from case, unaided, under 10 min | D36: The design is ambiguous. Fix keying and labelling, re-run
A37: Reliability tripwire | B37: any | C37: Two consecutive sessions needing tools to get running | D37: Stop adding features. Everything here is downstream of it working

Sheet Weight Budget
A1: Weight Budget - the constraint that is discovered at the check-in desk
A2: Blue = your input. Replace each estimate with an ACTUAL as parts get built and weighed. Size fails visibly; weight fails invisibly.
A4: Subsystem | B4: Item detail | C4: Est. (kg) | D4: Actual (kg) | E4: Using (kg) | F4: Flies? | G4: Note
A5: Motor | B5: GM6020 - 468 g confirmed from manufacturer user guide | C5: 0.47 | E5: =IF(D5="",C5,D5) -> 0.47 | F5: Yes
A6: Head structure | B6: Hub, 4 arms, plate carriers, balance masses | C6: 1.8 | E6: =IF(D6="",C6,D6) -> 1.8 | F6: Yes
A7: Armor plates | B7: 4 x custom small-format plates with sensors bonded | C7: 1.6 | E7: =IF(D7="",C7,D7) -> 1.6 | F7: Yes
A8: Rotating electronics | B8: Head MCU, front end, slip ring, wiring | C8: 0.3 | E8: =IF(D8="",C8,D8) -> 0.3 | F8: Yes
A9: Base electronics | B9: Controller, universal-input 24V PSU, enclosure, E-stop | C9: 1.5 | E9: =IF(D9="",C9,D9) -> 1.5 | F9: Yes
A10: Travel stand | B10: Legs, column, feet, latches - LARGEST UNCERTAINTY | C10: 3.5 | E10: =IF(D10="",C10,D10) -> 3.5 | F10: Yes
A11: Spares kit | B11: Piezo modules, spare plate face, latches, fasteners | C11: 0.8 | E11: =IF(D11="",C11,D11) -> 0.8 | F11: Yes
A12: Case + foam | B12: Shell, cut foam, corner protection - heavier than expected | C12: 4.5 | E12: =IF(D12="",C12,D12) -> 4.5 | F12: Yes
A13: Cables + PSU lead | B13: Mains lead, DC leads, spare connectors | C13: 0.4 | E13: =IF(D13="",C13,D13) -> 0.4 | F13: Yes
A14: Workshop base | B14: Ballasted steel pedestal - stays in Singapore | C14: 12 | E14: =IF(D14="",C14,D14) -> 12 | F14: No
A15: Rail assembly | B15: Extrusion, carriage, belt, motor - stays in Singapore | C15: 15 | E15: =IF(D15="",C15,D15) -> 15 | F15: No
B17: SUBTOTAL - items that fly | E17: =SUMIF(F5:F15,"Yes",E5:E15) -> 14.87
B18: Contingency (% - appropriate before any part exists) | D18: 0.25 | E18: =E17*D18 -> 3.7175
B19: PROJECTED PACKED WEIGHT | C19: =E17+E18 -> 18.5875
B21: Airline limit (kg) | C21: 23
B22: Internal target (kg) - margin for a heavier case than planned | C22: 20
B23: MARGIN vs. airline limit (kg) | C23: =C21-C19 -> 4.4125
B24: VERDICT | C24: =IF(C19<=C22,"PASS with margin",IF(C19<=C21,"PASS - tight","FAIL - over limit")) -> PASS with margin
A26: The stand and the case are ~44% of flying mass and are the two least-defined items. Build and weigh both EARLY in Phase 4, not at the end.
A27: Source: GM6020 mass from the RoboMaster GM6020 Brushless DC Motor User Guide. Every other figure is an estimate until an Actual is entered.

Sheet Packing
A1: Case Sizing + Packing Manifest
A2: 158 cm is a SUM of the three dimensions, not a length. Case shape is a free design variable - choose it AFTER the largest irreducible part is known.
A4: CASE DIMENSIONS (external, cm)
A5: Blue = your input. Set these once the part list is final.
A7: Length | C7: 85
A8: Width | C8: 45
A9: Height | C9: 28
A11: LINEAR SUM (L+W+H) | C11: =C7+C8+C9 -> 158
A12: Airline limit | C12: =158 -> 158
A13: Margin (cm) | C13: =C12-C11 -> 0
A14: VERDICT | C14: =IF(C11<=158,"PASS","FAIL - over limit") -> PASS
A15: Longest internal member (cm, approx.) | C15: =C7-4 -> 81
A16: Internal diagonal (cm) | C16: =SQRT((C7-4)^2+(C8-4)^2+(C9-4)^2) -> 93.904207
A19: CASE SHAPE OPTIONS - all sum to ~158 cm
A20: Shape (L x W x H, cm) | B20: Sum | C20: Longest member | D20: Comment
A21: 70 x 48 x 40 | B21: 158 | C21: ~66 cm | D21: Conventional suitcase proportions. Easy to handle, poor length.
A22: 85 x 45 x 28 | B22: 158 | C22: ~81 cm | D22: Balanced. Current working assumption above.
A23: 105 x 32 x 20 | B23: 157 | C23: ~101 cm | D23: Ski/golf-case proportions. Best length, awkward, more bending risk.
A24: 120 x 24 x 14 | B24: 158 | C24: ~116 cm | D24: Extreme. Fragile as a case, hard to protect. Not recommended.
A27: PACKING MANIFEST - one row per part. An empty foam pocket is a visible missing part.
A28: Part | B28: Qty | C28: Longest dim (cm) | D28: Mass each (kg) | E28: Total (kg) | F28: Foam pocket # | G28: Packed?
A29: Head hub with motor | B29: 1 | C29: 22 | D29: 1.1 | E29: =B29*D29 -> 1.1 | F29: P1 | G29: No
A30: Head arm + plate carrier | B30: 4 | C30: 20 | D30: 0.18 | E30: =B30*D30 -> 0.72 | F30: P2-P5 | G30: No
A31: Armor plate assembly | B31: 4 | C31: 15 | D31: 0.4 | E31: =B31*D31 -> 1.6 | F31: P6-P9 | G31: No
A32: Stand column section | B32: 2 | C32: 45 | D32: 0.6 | E32: =B32*D32 -> 1.2 | F32: P10-P11 | G32: No
A33: Stand leg | B33: 3 | C33: 50 | D33: 0.55 | E33: =B33*D33 -> 1.65 | F33: P12-P14 | G33: No
A34: Stand foot / ballast pocket | B34: 3 | C34: 12 | D34: 0.1 | E34: =B34*D34 -> 0.3 | F34: P15-P17 | G34: No
A35: Electronics enclosure | B35: 1 | C35: 25 | D35: 1.5 | E35: =B35*D35 -> 1.5 | F35: P18 | G35: No
A36: PSU + mains lead | B36: 1 | C36: 20 | D36: 0.4 | E36: =B36*D36 -> 0.4 | F36: P19 | G36: No
A37: Cable set | B37: 1 | C37: 15 | D37: 0.2 | E37: =B37*D37 -> 0.2 | F37: P20 | G37: No
A38: Spares kit box | B38: 1 | C38: 20 | D38: 0.8 | E38: =B38*D38 -> 0.8 | F38: P21 | G38: No
A39: Setup card + customs list | B39: 1 | C39: 30 | D39: 0.05 | E39: =B39*D39 -> 0.05 | F39: lid | G39: No
D41: CONTENTS TOTAL (kg) | E41: =SUM(E29:E39) -> 9.52
D42: Longest part (cm) | E42: =MAX(C29:C39) -> 50
D43: Fits the case? | E43: =IF(E42<=C15,"YES","NO - part is longer than the case interior") -> YES
D44: Items packed | E44: =COUNTIF(G29:G39,"Yes")&" / "&COUNTA(A29:A39) -> 0 / 11
A46: Part dimensions and masses are placeholders until real parts exist. Update them as you build - this tab is the single source of truth for the Dashboard transport check.

Sheet BOM
A1: Bill of Materials
A2: Blue = your input. Phase column lets you stage funding: Phases 1-2 deliver the training tool, Phases 3-4 add measurement and portability.
A4: Group | B4: Item | C4: Phase | D4: Qty | E4: Unit $ | F4: Line $ | G4: Own?
A5: Head | B5: GM6020 gimbal motor (468 g, 1.2 Nm, 18 mm hollow shaft) | C5: 1 | D5: 1 | E5: 110 | F5: =D5*E5 -> 110 | G5: Likely
A6: Head | B6: Hub + arm stock, plate carriers, balance masses | C6: 1 | D6: 1 | E6: 80 | F6: =D6*E6 -> 80 | G6: No
A7: Head | B7: Hardware: captive fasteners, latches, bearings | C7: 1 | D7: 1 | E7: 20 | F7: =D7*E7 -> 20 | G7: No
A8: Workshop base | B8: Steel plate, ballast, mounting hardware | C8: 1 | D8: 1 | E8: 40 | F8: =D8*E8 -> 40 | G8: Partly
A9: Rail | B9: Aluminium extrusion, 2.5-3 m | C9: 2 | D9: 1 | E9: 90 | F9: =D9*E9 -> 90 | G9: No
A10: Rail | B10: V-wheel carriage, GT belt, pulleys, idlers | C10: 2 | D10: 1 | E10: 55 | F10: =D10*E10 -> 55 | G10: No
A11: Rail | B11: Drive motor + limit switches | C11: 2 | D11: 1 | E11: 45 | F11: =D11*E11 -> 45 | G11: Maybe
A12: Plates | B12: 4 x plate substrate + replaceable impact faces | C12: 3 | D12: 4 | E12: 22 | F12: =D12*E12 -> 88 | G12: No
A13: Plates | B13: Piezo elements | C13: 3 | D13: 16 | E13: 1.5 | F13: =D13*E13 -> 24 | G13: No
A14: Plates | B14: Analogue front end: comparators, op-amps, PCB | C14: 3 | D14: 4 | E14: 9.5 | F14: =D14*E14 -> 38 | G14: No
A15: Rotating elec. | B15: Head MCU board | C15: 3 | D15: 1 | E15: 20 | F15: =D15*E15 -> 20 | G15: No
A16: Rotating elec. | B16: Slip ring capsule, hollow-shaft compatible | C16: 3 | D16: 1 | E16: 35 | F16: =D16*E16 -> 35 | G16: No
... A25: Spares | B25: Piezo modules, spare plate face, latches, fasteners | C25: 4 | D25: 1 | E25: 50 | F25: =D25*E25 -> 50 | G25: No
E27: SUBTOTAL (all phases) | F27: =SUM(F5:F25) -> 1020
E28: Less items likely already owned | F28: =SUMIF(G5:G25,"Likely",F5:F25) -> 110
E29: LIKELY SPEND | F29: =F27-F28 -> 910
E31: Phase 1 (workshop target) | F31: =SUMIF(C5:C25,1,F5:F25) -> 360
E32: Phase 2 (rail) | F32: =SUMIF(C5:C25,2,F5:F25) -> 190
E33: Phase 3 (plates + electronics) | F33: =SUMIF(C5:C25,3,F5:F25) -> 230
E34: Phase 4 (travel kit) | F34: =SUMIF(C5:C25,4,F5:F25) -> 240
E36: Phases 1-2 only (the training tool) | F36: =F31+F32 -> 550
E37: Phases 3-4 (measurement + portability) | F37: =F33+F34 -> 470
A40: Staging option: fund Phases 1-2 now ($550, the training tool), decide Phases 3-4 at the Week 8 review - which also defers plate spend past the Week 10 gate.

Sheet Risks
A1: Risk Register
A2: Score = Impact x Likelihood (1-5 each). Blue = your scoring inputs. Review at every gate.
A4: ID | B4: Risk | C4: Imp | D4: Lik | E4: Score | F4: Severity | G4: Mitigation | H4: Review at
A5: R1 | B5: Slotted joints loosen under vibration and repeated impact | C5: 5 | D5: 4 | E5: =C5*D5 -> 20 | F5: =IF(E5>=15,"Critical",IF(E5>=9,"High",IF(E5>=4,"Medium","Low"))) -> Critical | G5: REQ-M9: separate locating from clamping in every joint. Endurance run and full joint re-check in Phase 1, not Phase 4. | H5: Wk 5
A6: R2 | B6: Only the builder can operate or fix it | C6: 5 | D6: 4 | E6: =C6*D6 -> 20 | F6: =IF(E6>=15,"Critical",IF(E6>=9,"High",IF(E6>=4,"Medium","Low"))) -> Critical | G6: M2 makes this a tested requirement, not an aspiration. Keying, labelling, self-test and a setup card in the case. A teammate runs Phase 1 acceptance. | H6: Wk 6
A7: R3 | B7: Weight creep pushes the packed kit past 23 kg | C7: 4 | D7: 4 | E7: =C7*D7 -> 16 | F7: =IF(E7>=15,"Critical",IF(E7>=9,"High",IF(E7>=4,"Medium","Low"))) -> Critical | G7: Weigh every part as it is made. Stand and case are 44% of flying mass and least defined - build and weigh them EARLY in Phase 4. | H7: Wk 20
A8: R4 | B8: Piezo bonds fatigue and silently corrupt localisation | C8: 4 | D8: 4 | E8: =C8*D8 -> 16 | F8: =IF(E8>=15,"Critical",IF(E8>=9,"High",IF(E8>=4,"Medium","Low"))) -> Critical | G8: REQ-E6 per-channel drift detection; field-replaceable modules; boot self-test on the Health screen. | H8: Wk 10
A9: R5 | B9: Solo builder, in-season workload, project stalls part-built | C9: 4 | D9: 4 | E9: =C9*D9 -> 16 | F9: =IF(E9>=15,"Critical",IF(E9>=9,"High",IF(E9>=4,"Medium","Low"))) -> Critical | G9: Phase 1 delivers standalone value in 6 weeks; every later phase is independently useful. Stopping at any phase is acceptable. | H9: Wk 6
A10: R6 | B10: Travel stand cannot be both packable and stable enough | C10: 4 | D10: 3 | E10: =C10*D10 -> 12 | F10: =IF(E10>=15,"Critical",IF(E10>=9,"High",IF(E10>=4,"Medium","Low"))) -> High | G10: Contained by the architecture - workshop use is unaffected. Ballast filled on site rather than chasing stiffness in the suitcase. | H10: Wk 18
A11: R7 | B11: No usable mains power at the competition venue | C11: 4 | D11: 3 | E11: =C11*D11 -> 12 | F11: =IF(E11>=15,"Critical",IF(E11>=9,"High",IF(E11>=4,"Medium","Low"))) -> High | G11: Dual DC input accepting a borrowed RM pack. No battery can be flown regardless. Confirm venue power (Q3). | H11: Wk 8
A12: R8 | B12: Case fails baggage handling; parts arrive damaged | C12: 4 | D12: 3 | E12: =C12*D12 -> 12 | F12: =IF(E12>=15,"Critical",IF(E12>=9,"High",IF(E12>=4,"Medium","Low"))) -> High | G12: Drop test before travelling. Spares kit inside the case. Irreplaceable electronics in hand luggage. | H12: Wk 22
A13: R9 | B13: GM6020 torque marginal once the head is fully built | C13: 3 | D13: 3 | E13: =C13*D13 -> 9 | F13: =IF(E13>=15,"Critical",IF(E13>=9,"High",IF(E13>=4,"Medium","Low"))) -> High | G13: Budget head inertia before building. Keep plate radius small - inertia scales with r^2, the cheapest lever available. | H13: Wk 4
A14: R10 | B14: Injury from the spinning head or projectiles | C14: 5 | D14: 2 | E14: =C14*D14 -> 10 | F14: =IF(E14>=15,"Critical",IF(E14>=9,"High",IF(E14>=4,"Medium","Low"))) -> High | G14: Hardware E-stop cutting motor power directly. Balance verification before first full-speed run. Captive fasteners. Eye protection. | H14: Wk 4
A15: R11 | B15: Slip ring wears or becomes intermittent | C15: 3 | D15: 3 | E15: =C15*D15 -> 9 | F15: =IF(E15>=15,"Critical",IF(E15>=9,"High",IF(E15>=4,"Medium","Low"))) -> High | G15: REQ-E1 keeps only power and digital across the interface. REQ-E3 keeps a wireless data path open as a fallback. | H15: Wk 11
A16: R12 | B16: Referee gear unusable on a non-robot fixture at a venue | C16: 2 | D16: 3 | E16: =C16*D16 -> 6 | F16: =IF(E16>=15,"Critical",IF(E16>=9,"High",IF(E16>=4,"Medium","Low"))) -> Medium | G16: Custom plates work standalone, so referee is a workshop cross-check not a dependency. Confirm the rules position (Q4). | H16: Wk 8
B18: Highest score: | E18: =MAX(E5:E16) -> 20
B19: Thresholds: Critical >=15, High >=9, Medium >=4, Low <4.

Sheet Metrics
A1: Success Metrics
A2: Blue = fill in as measurements land.
A4: ID | B4: Metric | C4: Target | D4: Actual | E4: Due | F4: Status | G4: Why it is the right measure
A5: M1 | B5: Setup time, case to first shot | C5: <= 10 min, one person, no tools | E5: Wk 24 | F5: Pending | G5: Decides whether it actually gets used
A6: M2 | B6: Use by someone who did not build it | C6: Team member runs a full session unaided, first attempt | E6: Wk 6 | F6: Pending | G6: The primary user test. Tests the design, not the builder's memory
A7: M3 | B7: Sessions between tool-requiring failures | C7: >= 20 | E7: ongoing | F7: Pending | G7: Encodes 'switch it on and start using it'
A8: M4 | B8: Packed size | C8: <= 158 cm linear, case included | E8: Wk 21 | F8: Pending | G8: Binary pass/fail at the check-in desk
A9: M5 | B9: Packed weight | C9: <= 23 kg, target <= 20 kg | E9: Wk 21 | F9: Pending | G9: 3 kg margin absorbs spares and a heavier case
A10: M6 | B10: Spin speed consistency | C10: <= 2% from commanded, 0.25-3.0 rev/s | E10: Wk 4 | F10: Pending | G10: Two sessions a week apart must be comparable
A11: M7 | B11: Hit localisation accuracy | C11: <= 25 mm RMS, >= 95% quadrant | E11: Wk 17 | F11: Pending | G11: Honest limit for piezo TDOA on a small plate
A12: M8 | B12: Adoption | C12: >= 8 team sessions in the first month, by >= 2 different people | E12: Wk 10 | F12: Pending | G12: A tool one person uses is a rig; a tool the team uses is equipment
B14: M2 and M8 are the pair that matter. Every other metric can be satisfied by a machine only its builder can operate.

Sheet Open Questions
A1: Open Questions
A2: Q1 and Q7 gate Week 1-2. Q1 can reorder the whole back half of the plan.
A4: ID | B4: Question | C4: Blocks | D4: Needed by | E4: Status | F4: Answer
A5: Q1 | B5: Which competition and date is the travel deadline? RMUL 2026 mainland sites ran Mar-May 2026, so this plan assumes the 2027 cycle (~Mar 2027). If the real date is earlier, Phase 4 must move ahead of Phase 3. | C5: All Phase 4 scheduling | D5: Wk 2 | E5: Open
A6: Q7 | B6: Do you have 3D printing and machining access, or is everything cut by hand? | C6: Realistic effort for every mechanical part | D6: Wk 1 | E6: Open
A7: Q6 | B7: What plate height above the floor matches the robots you most need to practise against? | C7: Stand height, therefore packed length | D7: Wk 3 | E7: Open
A8: Q2 | B8: Is the ~$830 budget approvable, or should it be staged at the Week 8 review? | C8: Phase 3 and 4 procurement | D8: Wk 4 | E8: Open
A9: Q5 | B9: How long is the workshop rail, and what mounting does the space allow? | C9: Phase 2 rail design | D9: Wk 5 | E9: Open
A10: Q3 | B10: Is mains power available near a usable test area in a competition pit? | C10: Power architecture and on-site fallback | D10: Wk 8 | E10: Open
A11: Q4 | B11: Can referee gear be used on a non-robot fixture at a venue, and is a spare set available? | C11: Whether referee cross-check extends beyond the workshop | D11: Wk 8 | E11: Open
